Dispatchy/__init__.py
dispatchy-0.0.1.dist-info/METADATA
dispatchy-0.0.1.dist-info/WHEEL
dispatchy-0.0.1.dist-info/top_level.txt
dispatchy-0.0.1.dist-info/RECORD
