Metadata-Version: 2.4
Name: dispatchy
Version: 0.0.1
Summary: A Python library for handling webhooks with ease.
Home-page: https://www.valkdevices.com
Author: PDX
Author-email: valkdevice@gmail.com
Classifier: Programming Language :: Python :: 3
Classifier: License :: OSI Approved :: MIT License
Classifier: Operating System :: OS Independent
Requires-Python: >=3.6
Requires-Dist: requests>=2.20.0
Dynamic: author
Dynamic: author-email
Dynamic: classifier
Dynamic: description
Dynamic: description-content-type
Dynamic: home-page
Dynamic: requires-dist
Dynamic: requires-python
Dynamic: summary
